artifact_lint_py-1.0.0.dist-info/licenses/LICENSE
lint/__init__.py
lint/config.py
lint/linter.py
lint/result.py
lint/rule.py
lint/status.py
lint/typing.py
artifact_lint_py-1.0.0.dist-info/METADATA
artifact_lint_py-1.0.0.dist-info/WHEEL
artifact_lint_py-1.0.0.dist-info/top_level.txt
artifact_lint_py-1.0.0.dist-info/RECORD
