Metadata-Version: 2.4
Name: artifact-lint-py
Version: 1.0.0
Summary: A python framework for developing artifact linters
Author-email: Ethan Balcik <ethanbalcik@ibm.com>
License-Expression: Apache-2.0
Project-URL: Homepage, https://github.com/whatsacomputertho/artifact-lint-py
Project-URL: Issues, https://github.com/whatsacomputertho/artifact-lint-py/issues
Keywords: artifact,lint,py,linter
Classifier: Programming Language :: Python :: 3
Classifier: Operating System :: OS Independent
Requires-Python: >=3.9
License-File: LICENSE
Requires-Dist: jsonschema
Provides-Extra: test
Requires-Dist: tox; extra == "test"
Requires-Dist: pytest; extra == "test"
Requires-Dist: pytest-mock; extra == "test"
Requires-Dist: pytest-cov; extra == "test"
Provides-Extra: build
Requires-Dist: build; extra == "build"
Provides-Extra: doc
Requires-Dist: sphinx; extra == "doc"
Requires-Dist: sphinx_rtd_theme; extra == "doc"
Dynamic: license-file
